[{
        "name": "Thịt, rau củ",
        "icon_url": "https://salt.tikicdn.com/ts/upload/de/54/94/ae3b13c34e38af922e599db09c91b92d.png",
        "url": "https://tiki.vn/thuc-pham-tuoi-song/c44792"
    },
    {
        "name": "Bách Hóa",
        "icon_url": "https://salt.tikicdn.com/ts/upload/3a/b3/d2/c195e52c2edfc88f6bbb61f5b05e7634.png",
        "url": "https://tiki.vn/bach-hoa-online/c4384"
    },
    {
        "name": "Nhà Cửa",
        "icon_url": "https://salt.tikicdn.com/ts/upload/98/e3/98/7ae203ed1a1e4687bb129cbee6660ff7.png",
        "url": "https://tiki.vn/nha-cua-doi-song/c1883"
    },
    {
        "name": "Thiết Bị Số",
        "icon_url": "https://salt.tikicdn.com/ts/upload/83/0e/1e/60baa5e22522923e10e15efb58b244f2.png",
        "url": "https://tiki.vn/thiet-bi-kts-phu-kien-so/c1815"
    },
    {
        "name": "Điện Thoại",
        "icon_url": "https://salt.tikicdn.com/ts/upload/6e/72/d7/26b7b6d4c79046cb1f462c5415a21db1.png",
        "url": "https://tiki.vn/dien-thoai-may-tinh-bang/c1789"
    },
    {
        "name": "Mẹ & Bé",
        "icon_url": "https://salt.tikicdn.com/ts/upload/ed/6c/63/817bd4dd84355c0609508fdcc2b13bc5.png",
        "url": "https://tiki.vn/do-choi-me-be/c2549"
    },
    {
        "name": "Làm Đẹp",
        "icon_url": "https://salt.tikicdn.com/ts/upload/17/de/bd/cf736cd19d0ef99d6ce0d5404f4f9e0b.png",
        "url": "https://tiki.vn/lam-dep-suc-khoe/c1520"
    },
    {
        "name": "Gia Dụng",
        "icon_url": "https://salt.tikicdn.com/ts/upload/df/65/8f/ff7234df2304c4e47ec20d6d7ac3666e.png",
        "url": "https://tiki.vn/dien-gia-dung/c1882"
    },
    {
        "name": "Thời trang nữ",
        "icon_url": "https://salt.tikicdn.com/ts/upload/2d/6d/6c/dad4016843f10cd24e40ef41bc3fdd50.png",
        "url": "https://tiki.vn/thoi-trang-nu/c931"
    },
    {
        "name": "Thời trang nam",
        "icon_url": "https://salt.tikicdn.com/ts/upload/ac/3b/24/d3457f16b9927b128e194c5ad7812946.png",
        "url": "https://tiki.vn/thoi-trang-nam/c915"
    },
    {
        "name": "Giày nữ",
        "icon_url": "https://salt.tikicdn.com/ts/upload/cb/2f/c9/1899a0ccb75c85b44b3ee07fe4b81b45.png",
        "url": "https://tiki.vn/giay-dep-nu/c1703"
    },
    {
        "name": "Túi nữ",
        "icon_url": "https://salt.tikicdn.com/ts/upload/12/23/9b/2e8e88375da6ac5049752b9aa688bde8.png",
        "url": "https://tiki.vn/tui-vi-nu/c976"
    },
    {
        "name": "Giày nam",
        "icon_url": "https://salt.tikicdn.com/ts/upload/c7/c8/f5/dbdedc6e44a092e9dc561bf7b5741ed7.png",
        "url": "https://tiki.vn/giay-dep-nam/c1686"
    },
    {
        "name": "Túi nam",
        "icon_url": "https://salt.tikicdn.com/ts/upload/bd/f1/28/fe1377b7f5669e0aaa39099b4e9f1c61.png",
        "url": "https://tiki.vn/tui-thoi-trang-nam/c27616"
    },
    {
        "name": "Balo & Vali",
        "icon_url": "https://salt.tikicdn.com/ts/upload/76/de/7d/99073ab0225f7011da6b6d85785c9aea.png",
        "url": "https://tiki.vn/balo-va-vali/c6000"
    },
    {
        "name": "Phụ kiện",
        "icon_url": "https://salt.tikicdn.com/ts/upload/56/b0/3e/42e3c8b91f7377258cd2b168233cf5ee.png",
        "url": "https://tiki.vn/phu-kien-thoi-trang/c27498"
    },
    {
        "name": "Đồng hồ",
        "icon_url": "https://salt.tikicdn.com/ts/upload/a6/2e/0b/2a8fc12a043c41eca48401523ec335c3.png",
        "url": "https://tiki.vn/dong-ho-va-trang-suc/c8371"
    },
    {
        "name": "Laptop",
        "icon_url": "https://salt.tikicdn.com/ts/upload/1a/40/87/2c07aa50ad5a528b3500b7a27ac4671c.png",
        "url": "https://tiki.vn/laptop-may-vi-tinh-linh-kien/c1846"
    },
    {
        "name": "Quốc Tế",
        "icon_url": "https://salt.tikicdn.com/ts/upload/99/f6/a8/ac0fcfddfa867fc4406e1314821cc2e5.png",
        "url": "https://tiki.vn/hang-quoc-te/c17166"
    },
    {
        "name": "Voucher",
        "icon_url": "https://salt.tikicdn.com/ts/upload/2b/6b/ee/91029f6a4a1f6a71fe474dd26c346691.png",
        "url": "https://tiki.vn/voucher-dich-vu/c11312"
    },
    {
        "name": "Xe",
        "icon_url": "https://salt.tikicdn.com/ts/upload/2f/83/02/e7f70a3cb84e07afd1125312ffaab473.png",
        "url": "https://tiki.vn/o-to-xe-may-xe-dap/c8594"
    },
    {
        "name": "Sách",
        "icon_url": "https://salt.tikicdn.com/ts/upload/69/4c/6a/97fd9be63da959ca97c885775a2d77b4.png",
        "url": "https://tiki.vn/nha-sach-tiki/c8322"
    },
    {
        "name": "Điện Tử",
        "icon_url": "https://salt.tikicdn.com/ts/upload/20/cf/db/754939b679f3b46f9477d6a53a9cbb46.png",
        "url": "https://tiki.vn/dien-tu-dien-lanh/c4221"
    },
    {
        "name": "Thể Thao",
        "icon_url": "https://salt.tikicdn.com/ts/upload/14/66/68/0b5eea3e42cd1c7f1223950d7def200f.png",
        "url": "https://tiki.vn/the-thao-da-ngoai/c1975"
    },
    {
        "name": "Máy Ảnh",
        "icon_url": "https://salt.tikicdn.com/ts/upload/48/1f/30/712703a8f542b594377a33ba33e04148.png",
        "url": "https://tiki.vn/may-anh/c1801"
    }
]